langsci/bib/bibnouns.py
langsci/bib/bibpatterns.py
langsci/bib/bibtools.py
langsci/catalog/catalogmetadata.py
langsci/catalog/langscipressorg_webcrawler.py
langsci/catalog/omp2yaml.py
langsci/catalog/onixtemplates.py
langsci/catalog/titlemapping.py
langsci/catalog/validation.py
langsci/catalog/validation_examples.py
langsci/conversion/converter_helpers.py
langsci/conversion/convertertools.py
langsci/imtvault/extractgll.py
langsci/imtvault/imtvaultconstants.py
langsci/imtvault/integrate_entities.py
langsci/imtvault/interlinear.py
langsci/imtvault/misextractions.py
langsci/imtvault/named_entities.py
langsci/imtvault/philosophicalnonsense.py
langsci/imtvault/transitiveclosure.py
langsci/imtvault/wikidata_exclude.py
langsci/imtvault/wikidata_ids.py
langsci/imtvault/wikidatagraph.py
langsci/latex/asciify.py
langsci/latex/delatex.py
langsci/latex/indextools.py
langsci/latex/langscibibtex.py
langsci/latex/sanity.py
langsci/latex/texpatterns.py
langsci/resources/lgrlist.py
langsci/resources/macroareas.py
langsci/services/analyzepaperhive.py
langsci/services/webglottolog.py
langsci/services/zenodo.py
langsci-0.0.48.dist-info/METADATA
langsci-0.0.48.dist-info/WHEEL
langsci-0.0.48.dist-info/RECORD
