Metadata-Version: 2.4
Name: langsci
Version: 0.0.48
Summary: Tools for open access books used at Language Science Press
Project-URL: Homepage, https://github.com/langsci/pypi
Project-URL: Bug Tracker, https://github.com/langsci/pypi/issues
Author-email: Sebastian Nordhoff <sebastian.nordhoff@glottotopia.de>
Classifier: Operating System :: OS Independent
Classifier: Programming Language :: Python :: 3
Requires-Python: >=3.6
Requires-Dist: langdetect
Requires-Dist: lxml
Requires-Dist: matplotlib
Requires-Dist: pycryptodome
Requires-Dist: random2
Requires-Dist: rdflib
Requires-Dist: requests
Requires-Dist: wptools
Provides-Extra: dev
